LICENSE
README.md
setup.py
openlimit/__init__.py
openlimit/rate_limiters.py
openlimit/redis_rate_limiters.py
openlimit.egg-info/PKG-INFO
openlimit.egg-info/SOURCES.txt
openlimit.egg-info/dependency_links.txt
openlimit.egg-info/requires.txt
openlimit.egg-info/top_level.txt
openlimit/buckets/__init__.py
openlimit/buckets/bucket.py
openlimit/buckets/redis_bucket.py
openlimit/utilities/__init__.py
openlimit/utilities/context_decorators.py
openlimit/utilities/token_counters.py
tests/test_rate_limiters.py
tests/test_redis_rate_limiters.py