Metadata-Version: 2.1
Name: openlimit
Version: 0.3.0
Summary: Rate limiter for the OpenAI API
Home-page: https://github.com/shobrook/openlimit
Author: shobrook
Author-email: shobrookj@gmail.com
License: MIT
Keywords: openai,rate-limit,limit,api,request,token,leaky-bucket,gcra,redis,asyncio
Requires-Python: >=3
License-File: LICENSE
